llama_index/readers/linear/__init__.py
llama_index/readers/linear/base.py
llama_index_readers_linear-0.4.1.dist-info/METADATA
llama_index_readers_linear-0.4.1.dist-info/WHEEL
llama_index_readers_linear-0.4.1.dist-info/licenses/LICENSE
llama_index_readers_linear-0.4.1.dist-info/RECORD
