Metadata-Version: 2.4
Name: llama-index-readers-linear
Version: 0.4.1
Summary: llama-index readers linear integration
Author-email: Your Name <you@example.com>
Maintainer: Sushmithamallesh
License-Expression: MIT
License-File: LICENSE
Keywords: linear
Requires-Python: <4.0,>=3.9
Requires-Dist: gql<4,>=3.5.0
Requires-Dist: llama-index-core<0.15,>=0.13.0
Requires-Dist: requests<3,>=2.31.0
